<collection name="378">
  <page number="coverblank" label="coverblank" type="blank">
    <image type="TC" jp2Path="" width="0" height="0" />
    <image type="NC" jp2Path="" width="0" height="0" />
  </page>
  <page number="fob" label="Front outside binding" type="folio">
    <image type="TC" jp2Path="Parker/MS_378/JP2_MS_378_TC/378_fob_TC_46.jp2" width="4400" height="5951" />
    <image type="NC" jp2Path="Parker/MS_378/JP2_MS_378_NC/378_fob_NC_46.jp2" width="5428" height="7228" />
  </page>
  <page number="fib" label="Front inside binding" type="folio">
    <image type="TC" jp2Path="Parker/MS_378/JP2_MS_378_TC/378_fib_TC_46.jp2" width="4027" height="5985" />
    <image type="NC" jp2Path="Parker/MS_378/JP2_MS_378_NC/378_fib_NC_46.jp2" width="5428" height="7228" />
  </page>
  <page number="iR" label="f. i R" type="folio">
    <image type="TC" jp2Path="Parker/MS_378/JP2_MS_378_TC/378_i_R_TC_46.jp2" width="3830" height="5796" />
    <image type="NC" jp2Path="Parker/MS_378/JP2_MS_378_NC/378_i_R_NC_46.jp2" width="5428" height="7228" />
  </page>
  <page number="iV" label="f. i V" type="folio">
    <image type="TC" jp2Path="Parker/MS_378/JP2_MS_378_TC/378_i_V_TC_46.jp2" width="3800" height="5793" />
    <image type="NC" jp2Path="Parker/MS_378/JP2_MS_378_NC/378_i_V_NC_46.jp2" width="5428" height="7228" />
  </page>
  <page number="iiR" label="f. ii R" type="folio">
    <image type="TC" jp2Path="Parker/MS_378/JP2_MS_378_TC/378_ii_R_TC_46.jp2" width="3794" height="5784" />
    <image type="NC" jp2Path="Parker/MS_378/JP2_MS_378_NC/378_ii_R_NC_46.jp2" width="5428" height="7228" />
  </page>
  <page number="iiV" label="f. ii V" type="folio">
    <image type="TC" jp2Path="Parker/MS_378/JP2_MS_378_TC/378_ii_V_TC_46.jp2" width="3775" height="5781" />
    <image type="NC" jp2Path="Parker/MS_378/JP2_MS_378_NC/378_ii_V_NC_46.jp2" width="5428" height="7228" />
  </page>
  <page number="1R" label="f. 1 R" type="folio">
    <image type="TC" jp2Path="Parker/MS_378/JP2_MS_378_TC/378_001_R_TC_46.jp2" width="3838" height="5772" />
    <image type="NC" jp2Path="Parker/MS_378/JP2_MS_378_NC/378_001_R_NC_46.jp2" width="5428" height="7228" />
  </page>
  <page number="1V" label="f. 1 V" type="folio">
    <image type="TC" jp2Path="Parker/MS_378/JP2_MS_378_TC/378_001_V_TC_46.jp2" width="3758" height="5751" />
    <image type="NC" jp2Path="Parker/MS_378/JP2_MS_378_NC/378_001_V_NC_46.jp2" width="5428" height="7228" />
  </page>
  <page number="2R" label="f. 2 R" type="folio">
    <image type="TC" jp2Path="Parker/MS_378/JP2_MS_378_TC/378_002_R_TC_46.jp2" width="3753" height="5802" />
    <image type="NC" jp2Path="Parker/MS_378/JP2_MS_378_NC/378_002_R_NC_46.jp2" width="5428" height="7228" />
  </page>
  <page number="2V" label="f. 2 V" type="folio">
    <image type="TC" jp2Path="Parker/MS_378/JP2_MS_378_TC/378_002_V_TC_46.jp2" width="3734" height="5799" />
    <image type="NC" jp2Path="Parker/MS_378/JP2_MS_378_NC/378_002_V_NC_46.jp2" width="5428" height="7228" />
  </page>
  <page number="3R" label="f. 3 R" type="folio">
    <image type="TC" jp2Path="Parker/MS_378/JP2_MS_378_TC/378_003_R_TC_46.jp2" width="3789" height="5802" />
    <image type="NC" jp2Path="Parker/MS_378/JP2_MS_378_NC/378_003_R_NC_46.jp2" width="5428" height="7228" />
  </page>
  <page number="3V" label="f. 3 V" type="folio">
    <image type="TC" jp2Path="Parker/MS_378/JP2_MS_378_TC/378_003_V_TC_46.jp2" width="3776" height="5780" />
    <image type="NC" jp2Path="Parker/MS_378/JP2_MS_378_NC/378_003_V_NC_46.jp2" width="5428" height="7228" />
  </page>
  <page number="4R" label="f. 4 R" type="folio">
    <image type="TC" jp2Path="Parker/MS_378/JP2_MS_378_TC/378_004_R_TC_46.jp2" width="3783" height="5796" />
    <image type="NC" jp2Path="Parker/MS_378/JP2_MS_378_NC/378_004_R_NC_46.jp2" width="5428" height="7228" />
  </page>
  <page number="4V" label="f. 4 V" type="folio">
    <image type="TC" jp2Path="Parker/MS_378/JP2_MS_378_TC/378_004_V_TC_46.jp2" width="3787" height="5786" />
    <image type="NC" jp2Path="Parker/MS_378/JP2_MS_378_NC/378_004_V_NC_46.jp2" width="5428" height="7228" />
  </page>
  <page number="5R" label="f. 5 R" type="folio">
    <image type="TC" jp2Path="Parker/MS_378/JP2_MS_378_TC/378_005_R_TC_46.jp2" width="3783" height="5784" />
    <image type="NC" jp2Path="Parker/MS_378/JP2_MS_378_NC/378_005_R_NC_46.jp2" width="5428" height="7228" />
  </page>
  <page number="5V" label="f. 5 V" type="folio">
    <image type="TC" jp2Path="Parker/MS_378/JP2_MS_378_TC/378_005_V_TC_46.jp2" width="3776" height="5757" />
    <image type="NC" jp2Path="Parker/MS_378/JP2_MS_378_NC/378_005_V_NC_46.jp2" width="5428" height="7228" />
  </page>
  <page number="6R" label="f. 6 R" type="folio">
    <image type="TC" jp2Path="Parker/MS_378/JP2_MS_378_TC/378_006_R_TC_46.jp2" width="3784" height="5790" />
    <image type="NC" jp2Path="Parker/MS_378/JP2_MS_378_NC/378_006_R_NC_46.jp2" width="5428" height="7228" />
  </page>
  <page number="6V" label="f. 6 V" type="folio">
    <image type="TC" jp2Path="Parker/MS_378/JP2_MS_378_TC/378_006_V_TC_46.jp2" width="3782" height="5781" />
    <image type="NC" jp2Path="Parker/MS_378/JP2_MS_378_NC/378_006_V_NC_46.jp2" width="5428" height="7228" />
  </page>
  <page number="7R" label="f. 7 R" type="folio">
    <image type="TC" jp2Path="Parker/MS_378/JP2_MS_378_TC/378_007_R_TC_46.jp2" width="3783" height="5772" />
    <image type="NC" jp2Path="Parker/MS_378/JP2_MS_378_NC/378_007_R_NC_46.jp2" width="5428" height="7228" />
  </page>
  <page number="7V" label="f. 7 V" type="folio">
    <image type="TC" jp2Path="Parker/MS_378/JP2_MS_378_TC/378_007_V_TC_46.jp2" width="3758" height="5751" />
    <image type="NC" jp2Path="Parker/MS_378/JP2_MS_378_NC/378_007_V_NC_46.jp2" width="5428" height="7228" />
  </page>
  <page number="8R" label="f. 8 R" type="folio">
    <image type="TC" jp2Path="Parker/MS_378/JP2_MS_378_TC/378_008_R_TC_46.jp2" width="3790" height="5772" />
    <image type="NC" jp2Path="Parker/MS_378/JP2_MS_378_NC/378_008_R_NC_46.jp2" width="5428" height="7228" />
  </page>
  <page number="8V" label="f. 8 V" type="folio">
    <image type="TC" jp2Path="Parker/MS_378/JP2_MS_378_TC/378_008_V_TC_46.jp2" width="3770" height="5768" />
    <image type="NC" jp2Path="Parker/MS_378/JP2_MS_378_NC/378_008_V_NC_46.jp2" width="5428" height="7228" />
  </page>
  <page number="9R" label="f. 9 R" type="folio">
    <image type="TC" jp2Path="Parker/MS_378/JP2_MS_378_TC/378_009_R_TC_46.jp2" width="3771" height="5760" />
    <image type="NC" jp2Path="Parker/MS_378/JP2_MS_378_NC/378_009_R_NC_46.jp2" width="5428" height="7228" />
  </page>
  <page number="9V" label="f. 9 V" type="folio">
    <image type="TC" jp2Path="Parker/MS_378/JP2_MS_378_TC/378_009_V_TC_46.jp2" width="3746" height="5751" />
    <image type="NC" jp2Path="Parker/MS_378/JP2_MS_378_NC/378_009_V_NC_46.jp2" width="5428" height="7228" />
  </page>
  <page number="10R" label="f. 10 R" type="folio">
    <image type="TC" jp2Path="Parker/MS_378/JP2_MS_378_TC/378_010_R_TC_46.jp2" width="3742" height="5766" />
    <image type="NC" jp2Path="Parker/MS_378/JP2_MS_378_NC/378_010_R_NC_46.jp2" width="5428" height="7228" />
  </page>
  <page number="10V" label="f. 10 V" type="folio">
    <image type="TC" jp2Path="Parker/MS_378/JP2_MS_378_TC/378_010_V_TC_46.jp2" width="3728" height="5793" />
    <image type="NC" jp2Path="Parker/MS_378/JP2_MS_378_NC/378_010_V_NC_46.jp2" width="5428" height="7228" />
  </page>
  <page number="11R" label="f. 11 R" type="folio">
    <image type="TC" jp2Path="Parker/MS_378/JP2_MS_378_TC/378_011_R_TC_46.jp2" width="3784" height="5772" />
    <image type="NC" jp2Path="Parker/MS_378/JP2_MS_378_NC/378_011_R_NC_46.jp2" width="5428" height="7228" />
  </page>
  <page number="11V" label="f. 11 V" type="folio">
    <image type="TC" jp2Path="Parker/MS_378/JP2_MS_378_TC/378_011_V_TC_46.jp2" width="3758" height="5762" />
    <image type="NC" jp2Path="Parker/MS_378/JP2_MS_378_NC/378_011_V_NC_46.jp2" width="5428" height="7228" />
  </page>
  <page number="12R" label="f. 12 R" type="folio">
    <image type="TC" jp2Path="Parker/MS_378/JP2_MS_378_TC/378_012_R_TC_46.jp2" width="3748" height="5772" />
    <image type="NC" jp2Path="Parker/MS_378/JP2_MS_378_NC/378_012_R_NC_46.jp2" width="5428" height="7228" />
  </page>
  <page number="12V" label="f. 12 V" type="folio">
    <image type="TC" jp2Path="Parker/MS_378/JP2_MS_378_TC/378_012_V_TC_46.jp2" width="3721" height="5774" />
    <image type="NC" jp2Path="Parker/MS_378/JP2_MS_378_NC/378_012_V_NC_46.jp2" width="5428" height="7228" />
  </page>
  <page number="13R" label="f. 13 R" type="folio">
    <image type="TC" jp2Path="Parker/MS_378/JP2_MS_378_TC/378_013_R_TC_46.jp2" width="3772" height="5796" />
    <image type="NC" jp2Path="Parker/MS_378/JP2_MS_378_NC/378_013_R_NC_46.jp2" width="5428" height="7228" />
  </page>
  <page number="13V" label="f. 13 V" type="folio">
    <image type="TC" jp2Path="Parker/MS_378/JP2_MS_378_TC/378_013_V_TC_46.jp2" width="3727" height="5781" />
    <image type="NC" jp2Path="Parker/MS_378/JP2_MS_378_NC/378_013_V_NC_46.jp2" width="5428" height="7228" />
  </page>
  <page number="14R" label="f. 14 R" type="folio">
    <image type="TC" jp2Path="Parker/MS_378/JP2_MS_378_TC/378_014_R_TC_46.jp2" width="3724" height="5796" />
    <image type="NC" jp2Path="Parker/MS_378/JP2_MS_378_NC/378_014_R_NC_46.jp2" width="5428" height="7228" />
  </page>
  <page number="14V" label="f. 14 V" type="folio">
    <image type="TC" jp2Path="Parker/MS_378/JP2_MS_378_TC/378_014_V_TC_46.jp2" width="3704" height="5793" />
    <image type="NC" jp2Path="Parker/MS_378/JP2_MS_378_NC/378_014_V_NC_46.jp2" width="5428" height="7228" />
  </page>
  <page number="15R" label="f. 15 R" type="folio">
    <image type="TC" jp2Path="Parker/MS_378/JP2_MS_378_TC/378_015_R_TC_46.jp2" width="3724" height="5796" />
    <image type="NC" jp2Path="Parker/MS_378/JP2_MS_378_NC/378_015_R_NC_46.jp2" width="5428" height="7228" />
  </page>
  <page number="15V" label="f. 15 V" type="folio">
    <image type="TC" jp2Path="Parker/MS_378/JP2_MS_378_TC/378_015_V_TC_46.jp2" width="3697" height="5781" />
    <image type="NC" jp2Path="Parker/MS_378/JP2_MS_378_NC/378_015_V_NC_46.jp2" width="5428" height="7228" />
  </page>
  <page number="16R" label="f. 16 R" type="folio">
    <image type="TC" jp2Path="Parker/MS_378/JP2_MS_378_TC/378_016_R_TC_46.jp2" width="3705" height="5796" />
    <image type="NC" jp2Path="Parker/MS_378/JP2_MS_378_NC/378_016_R_NC_46.jp2" width="5428" height="7228" />
  </page>
  <page number="16V" label="f. 16 V" type="folio">
    <image type="TC" jp2Path="Parker/MS_378/JP2_MS_378_TC/378_016_V_TC_46.jp2" width="3685" height="5775" />
    <image type="NC" jp2Path="Parker/MS_378/JP2_MS_378_NC/378_016_V_NC_46.jp2" width="5428" height="7228" />
  </page>
  <page number="17R" label="f. 17 R" type="folio">
    <image type="TC" jp2Path="Parker/MS_378/JP2_MS_378_TC/378_017_R_TC_46.jp2" width="3735" height="5778" />
    <image type="NC" jp2Path="Parker/MS_378/JP2_MS_378_NC/378_017_R_NC_46.jp2" width="5428" height="7228" />
  </page>
  <page number="17V" label="f. 17 V" type="folio">
    <image type="TC" jp2Path="Parker/MS_378/JP2_MS_378_TC/378_017_V_TC_46.jp2" width="3704" height="5762" />
    <image type="NC" jp2Path="Parker/MS_378/JP2_MS_378_NC/378_017_V_NC_46.jp2" width="5428" height="7228" />
  </page>
  <page number="18R" label="f. 18 R" type="folio">
    <image type="TC" jp2Path="Parker/MS_378/JP2_MS_378_TC/378_018_R_TC_46.jp2" width="3705" height="5730" />
    <image type="NC" jp2Path="Parker/MS_378/JP2_MS_378_NC/378_018_R_NC_46.jp2" width="5428" height="7228" />
  </page>
  <page number="18V" label="f. 18 V" type="folio">
    <image type="TC" jp2Path="Parker/MS_378/JP2_MS_378_TC/378_018_V_TC_46.jp2" width="3667" height="5738" />
    <image type="NC" jp2Path="Parker/MS_378/JP2_MS_378_NC/378_018_V_NC_46.jp2" width="5428" height="7228" />
  </page>
  <page number="19R" label="f. 19 R" type="folio">
    <image type="TC" jp2Path="Parker/MS_378/JP2_MS_378_TC/378_019_R_TC_46.jp2" width="3693" height="5814" />
    <image type="NC" jp2Path="Parker/MS_378/JP2_MS_378_NC/378_019_R_NC_46.jp2" width="5428" height="7228" />
  </page>
  <page number="19V" label="f. 19 V" type="folio">
    <image type="TC" jp2Path="Parker/MS_378/JP2_MS_378_TC/378_019_V_TC_46.jp2" width="3691" height="5805" />
    <image type="NC" jp2Path="Parker/MS_378/JP2_MS_378_NC/378_019_V_NC_46.jp2" width="5428" height="7228" />
  </page>
  <page number="20R" label="f. 20 R" type="folio">
    <image type="TC" jp2Path="Parker/MS_378/JP2_MS_378_TC/378_020_R_TC_46.jp2" width="3663" height="5772" />
    <image type="NC" jp2Path="Parker/MS_378/JP2_MS_378_NC/378_020_R_NC_46.jp2" width="5428" height="7228" />
  </page>
  <page number="20V" label="f. 20 V" type="folio">
    <image type="TC" jp2Path="Parker/MS_378/JP2_MS_378_TC/378_020_V_TC_46.jp2" width="3674" height="5757" />
    <image type="NC" jp2Path="Parker/MS_378/JP2_MS_378_NC/378_020_V_NC_46.jp2" width="5428" height="7228" />
  </page>
  <page number="21R" label="f. 21 R" type="folio">
    <image type="TC" jp2Path="Parker/MS_378/JP2_MS_378_TC/378_021_R_TC_46.jp2" width="3694" height="5826" />
    <image type="NC" jp2Path="Parker/MS_378/JP2_MS_378_NC/378_021_R_NC_46.jp2" width="5428" height="7228" />
  </page>
  <page number="21V" label="f. 21 V" type="folio">
    <image type="TC" jp2Path="Parker/MS_378/JP2_MS_378_TC/378_021_V_TC_46.jp2" width="3679" height="5805" />
    <image type="NC" jp2Path="Parker/MS_378/JP2_MS_378_NC/378_021_V_NC_46.jp2" width="5428" height="7228" />
  </page>
  <page number="22R" label="f. 22 R" type="folio">
    <image type="TC" jp2Path="Parker/MS_378/JP2_MS_378_TC/378_022_R_TC_46.jp2" width="3681" height="5766" />
    <image type="NC" jp2Path="Parker/MS_378/JP2_MS_378_NC/378_022_R_NC_46.jp2" width="5428" height="7228" />
  </page>
  <page number="22V" label="f. 22 V" type="folio">
    <image type="TC" jp2Path="Parker/MS_378/JP2_MS_378_TC/378_022_V_TC_46.jp2" width="3644" height="5781" />
    <image type="NC" jp2Path="Parker/MS_378/JP2_MS_378_NC/378_022_V_NC_46.jp2" width="5428" height="7228" />
  </page>
  <page number="23R" label="f. 23 R" type="folio">
    <image type="TC" jp2Path="Parker/MS_378/JP2_MS_378_TC/378_023_R_TC_46.jp2" width="3670" height="5796" />
    <image type="NC" jp2Path="Parker/MS_378/JP2_MS_378_NC/378_023_R_NC_46.jp2" width="5428" height="7228" />
  </page>
  <page number="23V" label="f. 23 V" type="folio">
    <image type="TC" jp2Path="Parker/MS_378/JP2_MS_378_TC/378_023_V_TC_46.jp2" width="3655" height="5793" />
    <image type="NC" jp2Path="Parker/MS_378/JP2_MS_378_NC/378_023_V_NC_46.jp2" width="5428" height="7228" />
  </page>
  <page number="24R" label="f. 24 R" type="folio">
    <image type="TC" jp2Path="Parker/MS_378/JP2_MS_378_TC/378_024_R_TC_46.jp2" width="3627" height="5784" />
    <image type="NC" jp2Path="Parker/MS_378/JP2_MS_378_NC/378_024_R_NC_46.jp2" width="5428" height="7228" />
  </page>
  <page number="24V" label="f. 24 V" type="folio">
    <image type="TC" jp2Path="Parker/MS_378/JP2_MS_378_TC/378_024_V_TC_46.jp2" width="3649" height="5787" />
    <image type="NC" jp2Path="Parker/MS_378/JP2_MS_378_NC/378_024_V_NC_46.jp2" width="5428" height="7228" />
  </page>
  <page number="25R" label="f. 25 R" type="folio">
    <image type="TC" jp2Path="Parker/MS_378/JP2_MS_378_TC/378_025_R_TC_46.jp2" width="3645" height="5754" />
    <image type="NC" jp2Path="Parker/MS_378/JP2_MS_378_NC/378_025_R_NC_46.jp2" width="5428" height="7228" />
  </page>
  <page number="25V" label="f. 25 V" type="folio">
    <image type="TC" jp2Path="Parker/MS_378/JP2_MS_378_TC/378_025_V_TC_46.jp2" width="3643" height="5781" />
    <image type="NC" jp2Path="Parker/MS_378/JP2_MS_378_NC/378_025_V_NC_46.jp2" width="5428" height="7228" />
  </page>
  <page number="26R" label="f. 26 R" type="folio">
    <image type="TC" jp2Path="Parker/MS_378/JP2_MS_378_TC/378_026_R_TC_46.jp2" width="3657" height="5742" />
    <image type="NC" jp2Path="Parker/MS_378/JP2_MS_378_NC/378_026_R_NC_46.jp2" width="5428" height="7228" />
  </page>
  <page number="26V" label="f. 26 V" type="folio">
    <image type="TC" jp2Path="Parker/MS_378/JP2_MS_378_TC/378_026_V_TC_46.jp2" width="3649" height="5745" />
    <image type="NC" jp2Path="Parker/MS_378/JP2_MS_378_NC/378_026_V_NC_46.jp2" width="5428" height="7228" />
  </page>
  <page number="27R" label="f. 27 R" type="folio">
    <image type="TC" jp2Path="Parker/MS_378/JP2_MS_378_TC/378_027_R_TC_46.jp2" width="3621" height="5772" />
    <image type="NC" jp2Path="Parker/MS_378/JP2_MS_378_NC/378_027_R_NC_46.jp2" width="5428" height="7228" />
  </page>
  <page number="27V" label="f. 27 V" type="folio">
    <image type="TC" jp2Path="Parker/MS_378/JP2_MS_378_TC/378_027_V_TC_46.jp2" width="3619" height="5763" />
    <image type="NC" jp2Path="Parker/MS_378/JP2_MS_378_NC/378_027_V_NC_46.jp2" width="5428" height="7228" />
  </page>
  <page number="28R" label="f. 28 R" type="folio">
    <image type="TC" jp2Path="Parker/MS_378/JP2_MS_378_TC/378_028_R_TC_46.jp2" width="3597" height="5796" />
    <image type="NC" jp2Path="Parker/MS_378/JP2_MS_378_NC/378_028_R_NC_46.jp2" width="5428" height="7228" />
  </page>
  <page number="28V" label="f. 28 V" type="folio">
    <image type="TC" jp2Path="Parker/MS_378/JP2_MS_378_TC/378_028_V_TC_46.jp2" width="3607" height="5793" />
    <image type="NC" jp2Path="Parker/MS_378/JP2_MS_378_NC/378_028_V_NC_46.jp2" width="5428" height="7228" />
  </page>
  <page number="29R" label="f. 29 R" type="folio">
    <image type="TC" jp2Path="Parker/MS_378/JP2_MS_378_TC/378_029_R_TC_46.jp2" width="3586" height="5760" />
    <image type="NC" jp2Path="Parker/MS_378/JP2_MS_378_NC/378_029_R_NC_46.jp2" width="5428" height="7228" />
  </page>
  <page number="29V" label="f. 29 V" type="folio">
    <image type="TC" jp2Path="Parker/MS_378/JP2_MS_378_TC/378_029_V_TC_46.jp2" width="3595" height="5756" />
    <image type="NC" jp2Path="Parker/MS_378/JP2_MS_378_NC/378_029_V_NC_46.jp2" width="5428" height="7228" />
  </page>
  <page number="30R" label="f. 30 R" type="folio">
    <image type="TC" jp2Path="Parker/MS_378/JP2_MS_378_TC/378_030_R_TC_46.jp2" width="3567" height="5754" />
    <image type="NC" jp2Path="Parker/MS_378/JP2_MS_378_NC/378_030_R_NC_46.jp2" width="5428" height="7228" />
  </page>
  <page number="30V" label="f. 30 V" type="folio">
    <image type="TC" jp2Path="Parker/MS_378/JP2_MS_378_TC/378_030_V_TC_46.jp2" width="3632" height="5776" />
    <image type="NC" jp2Path="Parker/MS_378/JP2_MS_378_NC/378_030_V_NC_46.jp2" width="5428" height="7228" />
  </page>
  <page number="31R" label="f. 31 R" type="folio">
    <image type="TC" jp2Path="Parker/MS_378/JP2_MS_378_TC/378_031_R_TC_46.jp2" width="3556" height="5742" />
    <image type="NC" jp2Path="Parker/MS_378/JP2_MS_378_NC/378_031_R_NC_46.jp2" width="5428" height="7228" />
  </page>
  <page number="31V" label="f. 31 V" type="folio">
    <image type="TC" jp2Path="Parker/MS_378/JP2_MS_378_TC/378_031_V_TC_46.jp2" width="3590" height="5745" />
    <image type="NC" jp2Path="Parker/MS_378/JP2_MS_378_NC/378_031_V_NC_46.jp2" width="5428" height="7228" />
  </page>
  <page number="32R" label="f. 32 R" type="folio">
    <image type="TC" jp2Path="Parker/MS_378/JP2_MS_378_TC/378_032_R_TC_46.jp2" width="3549" height="5754" />
    <image type="NC" jp2Path="Parker/MS_378/JP2_MS_378_NC/378_032_R_NC_46.jp2" width="5428" height="7228" />
  </page>
  <page number="32V" label="f. 32 V" type="folio">
    <image type="TC" jp2Path="Parker/MS_378/JP2_MS_378_TC/378_032_V_TC_46.jp2" width="3584" height="5781" />
    <image type="NC" jp2Path="Parker/MS_378/JP2_MS_378_NC/378_032_V_NC_46.jp2" width="5428" height="7228" />
  </page>
  <page number="33R" label="f. 33 R" type="folio">
    <image type="TC" jp2Path="Parker/MS_378/JP2_MS_378_TC/378_033_R_TC_46.jp2" width="3561" height="5706" />
    <image type="NC" jp2Path="Parker/MS_378/JP2_MS_378_NC/378_033_R_NC_46.jp2" width="5428" height="7228" />
  </page>
  <page number="33V" label="f. 33 V" type="folio">
    <image type="TC" jp2Path="Parker/MS_378/JP2_MS_378_TC/378_033_V_TC_46.jp2" width="3560" height="5727" />
    <image type="NC" jp2Path="Parker/MS_378/JP2_MS_378_NC/378_033_V_NC_46.jp2" width="5428" height="7228" />
  </page>
  <page number="34R" label="f. 34 R" type="folio">
    <image type="TC" jp2Path="Parker/MS_378/JP2_MS_378_TC/378_034_R_TC_46.jp2" width="3532" height="5724" />
    <image type="NC" jp2Path="Parker/MS_378/JP2_MS_378_NC/378_034_R_NC_46.jp2" width="5428" height="7228" />
  </page>
  <page number="34V" label="f. 34 V" type="folio">
    <image type="TC" jp2Path="Parker/MS_378/JP2_MS_378_TC/378_034_V_TC_46.jp2" width="3673" height="5727" />
    <image type="NC" jp2Path="Parker/MS_378/JP2_MS_378_NC/378_034_V_NC_46.jp2" width="5428" height="7228" />
  </page>
  <page number="35R" label="f. 35 R" type="folio">
    <image type="TC" jp2Path="Parker/MS_378/JP2_MS_378_TC/378_035_R_TC_46.jp2" width="3598" height="5736" />
    <image type="NC" jp2Path="Parker/MS_378/JP2_MS_378_NC/378_035_R_NC_46.jp2" width="5428" height="7228" />
  </page>
  <page number="35V" label="f. 35 V" type="folio">
    <image type="TC" jp2Path="Parker/MS_378/JP2_MS_378_TC/378_035_V_TC_46.jp2" width="3667" height="5715" />
    <image type="NC" jp2Path="Parker/MS_378/JP2_MS_378_NC/378_035_V_NC_46.jp2" width="5428" height="7228" />
  </page>
  <page number="36R" label="f. 36 R" type="folio">
    <image type="TC" jp2Path="Parker/MS_378/JP2_MS_378_TC/378_036_R_TC_46.jp2" width="3598" height="5790" />
    <image type="NC" jp2Path="Parker/MS_378/JP2_MS_378_NC/378_036_R_NC_46.jp2" width="5428" height="7228" />
  </page>
  <page number="36V" label="f. 36 V" type="folio">
    <image type="TC" jp2Path="Parker/MS_378/JP2_MS_378_TC/378_036_V_TC_46.jp2" width="3644" height="5745" />
    <image type="NC" jp2Path="Parker/MS_378/JP2_MS_378_NC/378_036_V_NC_46.jp2" width="5428" height="7228" />
  </page>
  <page number="37R" label="f. 37 R" type="folio">
    <image type="TC" jp2Path="Parker/MS_378/JP2_MS_378_TC/378_037_R_TC_46.jp2" width="3604" height="5784" />
    <image type="NC" jp2Path="Parker/MS_378/JP2_MS_378_NC/378_037_R_NC_46.jp2" width="5428" height="7228" />
  </page>
  <page number="37V" label="f. 37 V" type="folio">
    <image type="TC" jp2Path="Parker/MS_378/JP2_MS_378_TC/378_037_V_TC_46.jp2" width="3721" height="5769" />
    <image type="NC" jp2Path="Parker/MS_378/JP2_MS_378_NC/378_037_V_NC_46.jp2" width="5428" height="7228" />
  </page>
  <page number="38R" label="f. 38 R" type="folio">
    <image type="TC" jp2Path="Parker/MS_378/JP2_MS_378_TC/378_038_R_TC_46.jp2" width="3609" height="5802" />
    <image type="NC" jp2Path="Parker/MS_378/JP2_MS_378_NC/378_038_R_NC_46.jp2" width="5428" height="7228" />
  </page>
  <page number="38V" label="f. 38 V" type="folio">
    <image type="TC" jp2Path="Parker/MS_378/JP2_MS_378_TC/378_038_V_TC_46.jp2" width="3704" height="5781" />
    <image type="NC" jp2Path="Parker/MS_378/JP2_MS_378_NC/378_038_V_NC_46.jp2" width="5428" height="7228" />
  </page>
  <page number="39R" label="f. 39 R" type="folio">
    <image type="TC" jp2Path="Parker/MS_378/JP2_MS_378_TC/378_039_R_TC_46.jp2" width="3609" height="5802" />
    <image type="NC" jp2Path="Parker/MS_378/JP2_MS_378_NC/378_039_R_NC_46.jp2" width="5428" height="7228" />
  </page>
  <page number="39V" label="f. 39 V" type="folio">
    <image type="TC" jp2Path="Parker/MS_378/JP2_MS_378_TC/378_039_V_TC_46.jp2" width="3661" height="5793" />
    <image type="NC" jp2Path="Parker/MS_378/JP2_MS_378_NC/378_039_V_NC_46.jp2" width="5428" height="7228" />
  </page>
  <page number="40R" label="f. 40 R" type="folio">
    <image type="TC" jp2Path="Parker/MS_378/JP2_MS_378_TC/378_040_R_TC_46.jp2" width="3622" height="5790" />
    <image type="NC" jp2Path="Parker/MS_378/JP2_MS_378_NC/378_040_R_NC_46.jp2" width="5428" height="7228" />
  </page>
  <page number="40V" label="f. 40 V" type="folio">
    <image type="TC" jp2Path="Parker/MS_378/JP2_MS_378_TC/378_040_V_TC_46.jp2" width="3667" height="5756" />
    <image type="NC" jp2Path="Parker/MS_378/JP2_MS_378_NC/378_040_V_NC_46.jp2" width="5428" height="7228" />
  </page>
  <page number="41R" label="f. 41 R" type="folio">
    <image type="TC" jp2Path="Parker/MS_378/JP2_MS_378_TC/378_041_R_TC_46.jp2" width="3622" height="5790" />
    <image type="NC" jp2Path="Parker/MS_378/JP2_MS_378_NC/378_041_R_NC_46.jp2" width="5428" height="7228" />
  </page>
  <page number="41V" label="f. 41 V" type="folio">
    <image type="TC" jp2Path="Parker/MS_378/JP2_MS_378_TC/378_041_V_TC_46.jp2" width="3667" height="5781" />
    <image type="NC" jp2Path="Parker/MS_378/JP2_MS_378_NC/378_041_V_NC_46.jp2" width="5428" height="7228" />
  </page>
  <page number="42R" label="f. 42 R" type="folio">
    <image type="TC" jp2Path="Parker/MS_378/JP2_MS_378_TC/378_042_R_TC_46.jp2" width="3621" height="5790" />
    <image type="NC" jp2Path="Parker/MS_378/JP2_MS_378_NC/378_042_R_NC_46.jp2" width="5428" height="7228" />
  </page>
  <page number="42V" label="f. 42 V" type="folio">
    <image type="TC" jp2Path="Parker/MS_378/JP2_MS_378_TC/378_042_V_TC_46.jp2" width="3661" height="5769" />
    <image type="NC" jp2Path="Parker/MS_378/JP2_MS_378_NC/378_042_V_NC_46.jp2" width="5428" height="7228" />
  </page>
  <page number="43R" label="f. 43 R" type="folio">
    <image type="TC" jp2Path="Parker/MS_378/JP2_MS_378_TC/378_043_R_TC_46.jp2" width="3624" height="5876" />
    <image type="NC" jp2Path="Parker/MS_378/JP2_MS_378_NC/378_043_R_NC_46.jp2" width="5428" height="7228" />
  </page>
  <page number="43V" label="f. 43 V" type="folio">
    <image type="TC" jp2Path="Parker/MS_378/JP2_MS_378_TC/378_043_V_TC_46.jp2" width="3745" height="5818" />
    <image type="NC" jp2Path="Parker/MS_378/JP2_MS_378_NC/378_043_V_NC_46.jp2" width="5428" height="7228" />
  </page>
  <page number="44R" label="f. 44 R" type="folio">
    <image type="TC" jp2Path="Parker/MS_378/JP2_MS_378_TC/378_044_R_TC_46.jp2" width="3687" height="5730" />
    <image type="NC" jp2Path="Parker/MS_378/JP2_MS_378_NC/378_044_R_NC_46.jp2" width="5428" height="7228" />
  </page>
  <page number="44V" label="f. 44 V" type="folio">
    <image type="TC" jp2Path="Parker/MS_378/JP2_MS_378_TC/378_044_V_TC_46.jp2" width="3745" height="5721" />
    <image type="NC" jp2Path="Parker/MS_378/JP2_MS_378_NC/378_044_V_NC_46.jp2" width="5428" height="7228" />
  </page>
  <page number="45R" label="f. 45 R" type="folio">
    <image type="TC" jp2Path="Parker/MS_378/JP2_MS_378_TC/378_045_R_TC_46.jp2" width="3645" height="5772" />
    <image type="NC" jp2Path="Parker/MS_378/JP2_MS_378_NC/378_045_R_NC_46.jp2" width="5428" height="7228" />
  </page>
  <page number="45V" label="f. 45 V" type="folio">
    <image type="TC" jp2Path="Parker/MS_378/JP2_MS_378_TC/378_045_V_TC_46.jp2" width="3704" height="5751" />
    <image type="NC" jp2Path="Parker/MS_378/JP2_MS_378_NC/378_045_V_NC_46.jp2" width="5428" height="7228" />
  </page>
  <page number="46R" label="f. 46 R" type="folio">
    <image type="TC" jp2Path="Parker/MS_378/JP2_MS_378_TC/378_046_R_TC_46.jp2" width="3658" height="5784" />
    <image type="NC" jp2Path="Parker/MS_378/JP2_MS_378_NC/378_046_R_NC_46.jp2" width="5428" height="7228" />
  </page>
  <page number="46V" label="f. 46 V" type="folio">
    <image type="TC" jp2Path="Parker/MS_378/JP2_MS_378_TC/378_046_V_TC_46.jp2" width="3667" height="5756" />
    <image type="NC" jp2Path="Parker/MS_378/JP2_MS_378_NC/378_046_V_NC_46.jp2" width="5428" height="7228" />
  </page>
  <page number="47R" label="f. 47 R" type="folio">
    <image type="TC" jp2Path="Parker/MS_378/JP2_MS_378_TC/378_047_R_TC_46.jp2" width="3657" height="5778" />
    <image type="NC" jp2Path="Parker/MS_378/JP2_MS_378_NC/378_047_R_NC_46.jp2" width="5428" height="7228" />
  </page>
  <page number="47V" label="f. 47 V" type="folio">
    <image type="TC" jp2Path="Parker/MS_378/JP2_MS_378_TC/378_047_V_TC_46.jp2" width="3673" height="5775" />
    <image type="NC" jp2Path="Parker/MS_378/JP2_MS_378_NC/378_047_V_NC_46.jp2" width="5428" height="7228" />
  </page>
  <page number="48R" label="f. 48 R" type="folio">
    <image type="TC" jp2Path="Parker/MS_378/JP2_MS_378_TC/378_048_R_TC_46.jp2" width="3657" height="5755" />
    <image type="NC" jp2Path="Parker/MS_378/JP2_MS_378_NC/378_048_R_NC_46.jp2" width="5428" height="7228" />
  </page>
  <page number="48V" label="f. 48 V" type="folio">
    <image type="TC" jp2Path="Parker/MS_378/JP2_MS_378_TC/378_048_V_TC_46.jp2" width="3661" height="5750" />
    <image type="NC" jp2Path="Parker/MS_378/JP2_MS_378_NC/378_048_V_NC_46.jp2" width="5428" height="7228" />
  </page>
  <page number="49R" label="f. 49 R" type="folio">
    <image type="TC" jp2Path="Parker/MS_378/JP2_MS_378_TC/378_049_R_TC_46.jp2" width="3658" height="5784" />
    <image type="NC" jp2Path="Parker/MS_378/JP2_MS_378_NC/378_049_R_NC_46.jp2" width="5428" height="7228" />
  </page>
  <page number="49V" label="f. 49 V" type="folio">
    <image type="TC" jp2Path="Parker/MS_378/JP2_MS_378_TC/378_049_V_TC_46.jp2" width="3739" height="5775" />
    <image type="NC" jp2Path="Parker/MS_378/JP2_MS_378_NC/378_049_V_NC_46.jp2" width="5428" height="7228" />
  </page>
  <page number="50R" label="f. 50 R" type="folio">
    <image type="TC" jp2Path="Parker/MS_378/JP2_MS_378_TC/378_050_R_TC_46.jp2" width="3646" height="5784" />
    <image type="NC" jp2Path="Parker/MS_378/JP2_MS_378_NC/378_050_R_NC_46.jp2" width="5428" height="7228" />
  </page>
  <page number="50V" label="f. 50 V" type="folio">
    <image type="TC" jp2Path="Parker/MS_378/JP2_MS_378_TC/378_050_V_TC_46.jp2" width="3733" height="5774" />
    <image type="NC" jp2Path="Parker/MS_378/JP2_MS_378_NC/378_050_V_NC_46.jp2" width="5428" height="7228" />
  </page>
  <page number="51R" label="f. 51 R" type="folio">
    <image type="TC" jp2Path="Parker/MS_378/JP2_MS_378_TC/378_051_R_TC_46.jp2" width="3651" height="5802" />
    <image type="NC" jp2Path="Parker/MS_378/JP2_MS_378_NC/378_051_R_NC_46.jp2" width="5428" height="7228" />
  </page>
  <page number="51V" label="f. 51 V" type="folio">
    <image type="TC" jp2Path="Parker/MS_378/JP2_MS_378_TC/378_051_V_TC_46.jp2" width="3740" height="5806" />
    <image type="NC" jp2Path="Parker/MS_378/JP2_MS_378_NC/378_051_V_NC_46.jp2" width="5428" height="7228" />
  </page>
  <page number="52R" label="f. 52 R" type="folio">
    <image type="TC" jp2Path="Parker/MS_378/JP2_MS_378_TC/378_052_R_TC_46.jp2" width="3645" height="5784" />
    <image type="NC" jp2Path="Parker/MS_378/JP2_MS_378_NC/378_052_R_NC_46.jp2" width="5428" height="7228" />
  </page>
  <page number="52V" label="f. 52 V" type="folio">
    <image type="TC" jp2Path="Parker/MS_378/JP2_MS_378_TC/378_052_V_TC_46.jp2" width="3722" height="5775" />
    <image type="NC" jp2Path="Parker/MS_378/JP2_MS_378_NC/378_052_V_NC_46.jp2" width="5428" height="7228" />
  </page>
  <page number="53R" label="f. 53 R" type="folio">
    <image type="TC" jp2Path="Parker/MS_378/JP2_MS_378_TC/378_053_R_TC_46.jp2" width="3628" height="5748" />
    <image type="NC" jp2Path="Parker/MS_378/JP2_MS_378_NC/378_053_R_NC_46.jp2" width="5428" height="7228" />
  </page>
  <page number="53V" label="f. 53 V" type="folio">
    <image type="TC" jp2Path="Parker/MS_378/JP2_MS_378_TC/378_053_V_TC_46.jp2" width="3698" height="5751" />
    <image type="NC" jp2Path="Parker/MS_378/JP2_MS_378_NC/378_053_V_NC_46.jp2" width="5428" height="7228" />
  </page>
  <page number="54R" label="f. 54 R" type="folio">
    <image type="TC" jp2Path="Parker/MS_378/JP2_MS_378_TC/378_054_R_TC_46.jp2" width="3627" height="5742" />
    <image type="NC" jp2Path="Parker/MS_378/JP2_MS_378_NC/378_054_R_NC_46.jp2" width="5428" height="7228" />
  </page>
  <page number="54V" label="f. 54 V" type="folio">
    <image type="TC" jp2Path="Parker/MS_378/JP2_MS_378_TC/378_054_V_TC_46.jp2" width="3703" height="5745" />
    <image type="NC" jp2Path="Parker/MS_378/JP2_MS_378_NC/378_054_V_NC_46.jp2" width="5428" height="7228" />
  </page>
  <page number="55R" label="f. 55 R" type="folio">
    <image type="TC" jp2Path="Parker/MS_378/JP2_MS_378_TC/378_055_R_TC_46.jp2" width="3622" height="5778" />
    <image type="NC" jp2Path="Parker/MS_378/JP2_MS_378_NC/378_055_R_NC_46.jp2" width="5428" height="7228" />
  </page>
  <page number="55V" label="f. 55 V" type="folio">
    <image type="TC" jp2Path="Parker/MS_378/JP2_MS_378_TC/378_055_V_TC_46.jp2" width="3762" height="5775" />
    <image type="NC" jp2Path="Parker/MS_378/JP2_MS_378_NC/378_055_V_NC_46.jp2" width="5428" height="7228" />
  </page>
  <page number="56R" label="f. 56 R" type="folio">
    <image type="TC" jp2Path="Parker/MS_378/JP2_MS_378_TC/378_056_R_TC_46.jp2" width="3634" height="5766" />
    <image type="NC" jp2Path="Parker/MS_378/JP2_MS_378_NC/378_056_R_NC_46.jp2" width="5428" height="7228" />
  </page>
  <page number="56V" label="f. 56 V" type="folio">
    <image type="TC" jp2Path="Parker/MS_378/JP2_MS_378_TC/378_056_V_TC_46.jp2" width="3733" height="5750" />
    <image type="NC" jp2Path="Parker/MS_378/JP2_MS_378_NC/378_056_V_NC_46.jp2" width="5428" height="7228" />
  </page>
  <page number="57R" label="f. 57 R" type="folio">
    <image type="TC" jp2Path="Parker/MS_378/JP2_MS_378_TC/378_057_R_TC_46.jp2" width="3634" height="5814" />
    <image type="NC" jp2Path="Parker/MS_378/JP2_MS_378_NC/378_057_R_NC_46.jp2" width="5428" height="7228" />
  </page>
  <page number="57V" label="f. 57 V" type="folio">
    <image type="TC" jp2Path="Parker/MS_378/JP2_MS_378_TC/378_057_V_TC_46.jp2" width="3727" height="5817" />
    <image type="NC" jp2Path="Parker/MS_378/JP2_MS_378_NC/378_057_V_NC_46.jp2" width="5428" height="7228" />
  </page>
  <page number="58R" label="f. 58 R" type="folio">
    <image type="TC" jp2Path="Parker/MS_378/JP2_MS_378_TC/378_058_R_TC_46.jp2" width="3653" height="5796" />
    <image type="NC" jp2Path="Parker/MS_378/JP2_MS_378_NC/378_058_R_NC_46.jp2" width="5428" height="7228" />
  </page>
  <page number="58V" label="f. 58 V" type="folio">
    <image type="TC" jp2Path="Parker/MS_378/JP2_MS_378_TC/378_058_V_TC_46.jp2" width="3727" height="5768" />
    <image type="NC" jp2Path="Parker/MS_378/JP2_MS_378_NC/378_058_V_NC_46.jp2" width="5428" height="7228" />
  </page>
  <page number="59R" label="f. 59 R" type="folio">
    <image type="TC" jp2Path="Parker/MS_378/JP2_MS_378_TC/378_059_R_TC_46.jp2" width="3659" height="5814" />
    <image type="NC" jp2Path="Parker/MS_378/JP2_MS_378_NC/378_059_R_NC_46.jp2" width="5428" height="7228" />
  </page>
  <page number="59V" label="f. 59 V" type="folio">
    <image type="TC" jp2Path="Parker/MS_378/JP2_MS_378_TC/378_059_V_TC_46.jp2" width="3709" height="5805" />
    <image type="NC" jp2Path="Parker/MS_378/JP2_MS_378_NC/378_059_V_NC_46.jp2" width="5428" height="7228" />
  </page>
  <page number="60R" label="f. 60 R" type="folio">
    <image type="TC" jp2Path="Parker/MS_378/JP2_MS_378_TC/378_060_R_TC_46.jp2" width="3658" height="5845" />
    <image type="NC" jp2Path="Parker/MS_378/JP2_MS_378_NC/378_060_R_NC_46.jp2" width="5428" height="7228" />
  </page>
  <page number="60V" label="f. 60 V" type="folio">
    <image type="TC" jp2Path="Parker/MS_378/JP2_MS_378_TC/378_060_V_TC_46.jp2" width="3703" height="5859" />
    <image type="NC" jp2Path="Parker/MS_378/JP2_MS_378_NC/378_060_V_NC_46.jp2" width="5428" height="7228" />
  </page>
  <page number="61R" label="f. 61 R" type="folio">
    <image type="TC" jp2Path="Parker/MS_378/JP2_MS_378_TC/378_061_R_TC_46.jp2" width="3652" height="5796" />
    <image type="NC" jp2Path="Parker/MS_378/JP2_MS_378_NC/378_061_R_NC_46.jp2" width="5428" height="7228" />
  </page>
  <page number="61V" label="f. 61 V" type="folio">
    <image type="TC" jp2Path="Parker/MS_378/JP2_MS_378_TC/378_061_V_TC_46.jp2" width="3704" height="5787" />
    <image type="NC" jp2Path="Parker/MS_378/JP2_MS_378_NC/378_061_V_NC_46.jp2" width="5428" height="7228" />
  </page>
  <page number="62R" label="f. 62 R" type="folio">
    <image type="TC" jp2Path="Parker/MS_378/JP2_MS_378_TC/378_062_R_TC_46.jp2" width="3640" height="5796" />
    <image type="NC" jp2Path="Parker/MS_378/JP2_MS_378_NC/378_062_R_NC_46.jp2" width="5428" height="7228" />
  </page>
  <page number="62V" label="f. 62 V" type="folio">
    <image type="TC" jp2Path="Parker/MS_378/JP2_MS_378_TC/378_062_V_TC_46.jp2" width="3685" height="5787" />
    <image type="NC" jp2Path="Parker/MS_378/JP2_MS_378_NC/378_062_V_NC_46.jp2" width="5428" height="7228" />
  </page>
  <page number="63R" label="f. 63 R" type="folio">
    <image type="TC" jp2Path="Parker/MS_378/JP2_MS_378_TC/378_063_R_TC_46.jp2" width="3604" height="5711" />
    <image type="NC" jp2Path="Parker/MS_378/JP2_MS_378_NC/378_063_R_NC_46.jp2" width="5428" height="7228" />
  </page>
  <page number="63V" label="f. 63 V" type="folio">
    <image type="TC" jp2Path="Parker/MS_378/JP2_MS_378_TC/378_063_V_TC_46.jp2" width="3673" height="5679" />
    <image type="NC" jp2Path="Parker/MS_378/JP2_MS_378_NC/378_063_V_NC_46.jp2" width="5428" height="7228" />
  </page>
  <page number="64R" label="f. 64 R" type="folio">
    <image type="TC" jp2Path="Parker/MS_378/JP2_MS_378_TC/378_064_R_TC_46.jp2" width="3615" height="5748" />
    <image type="NC" jp2Path="Parker/MS_378/JP2_MS_378_NC/378_064_R_NC_46.jp2" width="5428" height="7228" />
  </page>
  <page number="64V" label="f. 64 V" type="folio">
    <image type="TC" jp2Path="Parker/MS_378/JP2_MS_378_TC/378_064_V_TC_46.jp2" width="3661" height="5751" />
    <image type="NC" jp2Path="Parker/MS_378/JP2_MS_378_NC/378_064_V_NC_46.jp2" width="5428" height="7228" />
  </page>
  <page number="65R" label="f. 65 R" type="folio">
    <image type="TC" jp2Path="Parker/MS_378/JP2_MS_378_TC/378_065_R_TC_46.jp2" width="3597" height="5772" />
    <image type="NC" jp2Path="Parker/MS_378/JP2_MS_378_NC/378_065_R_NC_46.jp2" width="5428" height="7228" />
  </page>
  <page number="65V" label="f. 65 V" type="folio">
    <image type="TC" jp2Path="Parker/MS_378/JP2_MS_378_TC/378_065_V_TC_46.jp2" width="3644" height="5775" />
    <image type="NC" jp2Path="Parker/MS_378/JP2_MS_378_NC/378_065_V_NC_46.jp2" width="5428" height="7228" />
  </page>
  <page number="66R" label="f. 66 R" type="folio">
    <image type="TC" jp2Path="Parker/MS_378/JP2_MS_378_TC/378_066_R_TC_46.jp2" width="3556" height="5694" />
    <image type="NC" jp2Path="Parker/MS_378/JP2_MS_378_NC/378_066_R_NC_46.jp2" width="5428" height="7228" />
  </page>
  <page number="66V" label="f. 66 V" type="folio">
    <image type="TC" jp2Path="Parker/MS_378/JP2_MS_378_TC/378_066_V_TC_46.jp2" width="3571" height="5685" />
    <image type="NC" jp2Path="Parker/MS_378/JP2_MS_378_NC/378_066_V_NC_46.jp2" width="5428" height="7228" />
  </page>
  <page number="67R" label="f. 67 R" type="folio">
    <image type="TC" jp2Path="Parker/MS_378/JP2_MS_378_TC/378_067_R_TC_46.jp2" width="3633" height="5677" />
    <image type="NC" jp2Path="Parker/MS_378/JP2_MS_378_NC/378_067_R_NC_46.jp2" width="5428" height="7228" />
  </page>
  <page number="67V" label="f. 67 V" type="folio">
    <image type="TC" jp2Path="Parker/MS_378/JP2_MS_378_TC/378_067_V_TC_46.jp2" width="3596" height="5666" />
    <image type="NC" jp2Path="Parker/MS_378/JP2_MS_378_NC/378_067_V_NC_46.jp2" width="5428" height="7228" />
  </page>
  <page number="68R" label="f. 68 R" type="folio">
    <image type="TC" jp2Path="Parker/MS_378/JP2_MS_378_TC/378_068_R_TC_46.jp2" width="3562" height="5711" />
    <image type="NC" jp2Path="Parker/MS_378/JP2_MS_378_NC/378_068_R_NC_46.jp2" width="5428" height="7228" />
  </page>
  <page number="68V" label="f. 68 V" type="folio">
    <image type="TC" jp2Path="Parker/MS_378/JP2_MS_378_TC/378_068_V_TC_46.jp2" width="3565" height="5691" />
    <image type="NC" jp2Path="Parker/MS_378/JP2_MS_378_NC/378_068_V_NC_46.jp2" width="5428" height="7228" />
  </page>
  <page number="69R" label="f. 69 R" type="folio">
    <image type="TC" jp2Path="Parker/MS_378/JP2_MS_378_TC/378_069_R_TC_46.jp2" width="3556" height="5651" />
    <image type="NC" jp2Path="Parker/MS_378/JP2_MS_378_NC/378_069_R_NC_46.jp2" width="5428" height="7228" />
  </page>
  <page number="69V" label="f. 69 V" type="folio">
    <image type="TC" jp2Path="Parker/MS_378/JP2_MS_378_TC/378_069_V_TC_46.jp2" width="3572" height="5636" />
    <image type="NC" jp2Path="Parker/MS_378/JP2_MS_378_NC/378_069_V_NC_46.jp2" width="5428" height="7228" />
  </page>
  <page number="70R" label="f. 70 R" type="folio">
    <image type="TC" jp2Path="Parker/MS_378/JP2_MS_378_TC/378_070_R_TC_46.jp2" width="3550" height="5652" />
    <image type="NC" jp2Path="Parker/MS_378/JP2_MS_378_NC/378_070_R_NC_46.jp2" width="5428" height="7228" />
  </page>
  <page number="70V" label="f. 70 V" type="folio">
    <image type="TC" jp2Path="Parker/MS_378/JP2_MS_378_TC/378_070_V_TC_46.jp2" width="3566" height="5654" />
    <image type="NC" jp2Path="Parker/MS_378/JP2_MS_378_NC/378_070_V_NC_46.jp2" width="5428" height="7228" />
  </page>
  <page number="71R" label="f. 71 R" type="folio">
    <image type="TC" jp2Path="Parker/MS_378/JP2_MS_378_TC/378_071_R_TC_46.jp2" width="3639" height="5664" />
    <image type="NC" jp2Path="Parker/MS_378/JP2_MS_378_NC/378_071_R_NC_46.jp2" width="5428" height="7228" />
  </page>
  <page number="71V" label="f. 71 V" type="folio">
    <image type="TC" jp2Path="Parker/MS_378/JP2_MS_378_TC/378_071_V_TC_46.jp2" width="3571" height="5666" />
    <image type="NC" jp2Path="Parker/MS_378/JP2_MS_378_NC/378_071_V_NC_46.jp2" width="5428" height="7228" />
  </page>
  <page number="72R" label="f. 72 R" type="folio">
    <image type="TC" jp2Path="Parker/MS_378/JP2_MS_378_TC/378_072_R_TC_46.jp2" width="3621" height="5706" />
    <image type="NC" jp2Path="Parker/MS_378/JP2_MS_378_NC/378_072_R_NC_46.jp2" width="5428" height="7228" />
  </page>
  <page number="72V" label="f. 72 V" type="folio">
    <image type="TC" jp2Path="Parker/MS_378/JP2_MS_378_TC/378_072_V_TC_46.jp2" width="3601" height="5679" />
    <image type="NC" jp2Path="Parker/MS_378/JP2_MS_378_NC/378_072_V_NC_46.jp2" width="5428" height="7228" />
  </page>
  <page number="73R" label="f. 73 R" type="folio">
    <image type="TC" jp2Path="Parker/MS_378/JP2_MS_378_TC/378_073_R_TC_46.jp2" width="3614" height="5766" />
    <image type="NC" jp2Path="Parker/MS_378/JP2_MS_378_NC/378_073_R_NC_46.jp2" width="5428" height="7228" />
  </page>
  <page number="73V" label="f. 73 V" type="folio">
    <image type="TC" jp2Path="Parker/MS_378/JP2_MS_378_TC/378_073_V_TC_46.jp2" width="3578" height="5733" />
    <image type="NC" jp2Path="Parker/MS_378/JP2_MS_378_NC/378_073_V_NC_46.jp2" width="5428" height="7228" />
  </page>
  <page number="74R" label="f. 74 R" type="folio">
    <image type="TC" jp2Path="Parker/MS_378/JP2_MS_378_TC/378_074_R_TC_46.jp2" width="3650" height="5719" />
    <image type="NC" jp2Path="Parker/MS_378/JP2_MS_378_NC/378_074_R_NC_46.jp2" width="5428" height="7228" />
  </page>
  <page number="74V" label="f. 74 V" type="folio">
    <image type="TC" jp2Path="Parker/MS_378/JP2_MS_378_TC/378_074_V_TC_46.jp2" width="3601" height="5709" />
    <image type="NC" jp2Path="Parker/MS_378/JP2_MS_378_NC/378_074_V_NC_46.jp2" width="5428" height="7228" />
  </page>
  <page number="75R" label="f. 75 R" type="folio">
    <image type="TC" jp2Path="Parker/MS_378/JP2_MS_378_TC/378_075_R_TC_46.jp2" width="3644" height="5707" />
    <image type="NC" jp2Path="Parker/MS_378/JP2_MS_378_NC/378_075_R_NC_46.jp2" width="5428" height="7228" />
  </page>
  <page number="75V" label="f. 75 V" type="folio">
    <image type="TC" jp2Path="Parker/MS_378/JP2_MS_378_TC/378_075_V_TC_46.jp2" width="3596" height="5697" />
    <image type="NC" jp2Path="Parker/MS_378/JP2_MS_378_NC/378_075_V_NC_46.jp2" width="5428" height="7228" />
  </page>
  <page number="76R" label="f. 76 R" type="folio">
    <image type="TC" jp2Path="Parker/MS_378/JP2_MS_378_TC/378_076_R_TC_46.jp2" width="3608" height="5712" />
    <image type="NC" jp2Path="Parker/MS_378/JP2_MS_378_NC/378_076_R_NC_46.jp2" width="5428" height="7228" />
  </page>
  <page number="76V" label="f. 76 V" type="folio">
    <image type="TC" jp2Path="Parker/MS_378/JP2_MS_378_TC/378_076_V_TC_46.jp2" width="3578" height="5697" />
    <image type="NC" jp2Path="Parker/MS_378/JP2_MS_378_NC/378_076_V_NC_46.jp2" width="5428" height="7228" />
  </page>
  <page number="77R" label="f. 77 R" type="folio">
    <image type="TC" jp2Path="Parker/MS_378/JP2_MS_378_TC/378_077_R_TC_46.jp2" width="3608" height="5784" />
    <image type="NC" jp2Path="Parker/MS_378/JP2_MS_378_NC/378_077_R_NC_46.jp2" width="5428" height="7228" />
  </page>
  <page number="77V" label="f. 77 V" type="folio">
    <image type="TC" jp2Path="Parker/MS_378/JP2_MS_378_TC/378_077_V_TC_46.jp2" width="3583" height="5775" />
    <image type="NC" jp2Path="Parker/MS_378/JP2_MS_378_NC/378_077_V_NC_46.jp2" width="5428" height="7228" />
  </page>
  <page number="78R" label="f. 78 R" type="folio">
    <image type="TC" jp2Path="Parker/MS_378/JP2_MS_378_TC/378_078_R_TC_46.jp2" width="3620" height="5718" />
    <image type="NC" jp2Path="Parker/MS_378/JP2_MS_378_NC/378_078_R_NC_46.jp2" width="5428" height="7228" />
  </page>
  <page number="78V" label="f. 78 V" type="folio">
    <image type="TC" jp2Path="Parker/MS_378/JP2_MS_378_TC/378_078_V_TC_46.jp2" width="3590" height="5703" />
    <image type="NC" jp2Path="Parker/MS_378/JP2_MS_378_NC/378_078_V_NC_46.jp2" width="5428" height="7228" />
  </page>
  <page number="79R" label="f. 79 R" type="folio">
    <image type="TC" jp2Path="Parker/MS_378/JP2_MS_378_TC/378_079_R_TC_46.jp2" width="3614" height="5706" />
    <image type="NC" jp2Path="Parker/MS_378/JP2_MS_378_NC/378_079_R_NC_46.jp2" width="5428" height="7228" />
  </page>
  <page number="79V" label="f. 79 V" type="folio">
    <image type="TC" jp2Path="Parker/MS_378/JP2_MS_378_TC/378_079_V_TC_46.jp2" width="3614" height="5720" />
    <image type="NC" jp2Path="Parker/MS_378/JP2_MS_378_NC/378_079_V_NC_46.jp2" width="5428" height="7228" />
  </page>
  <page number="80R" label="f. 80 R" type="folio">
    <image type="TC" jp2Path="Parker/MS_378/JP2_MS_378_TC/378_080_R_TC_46.jp2" width="3638" height="5754" />
    <image type="NC" jp2Path="Parker/MS_378/JP2_MS_378_NC/378_080_R_NC_46.jp2" width="5428" height="7228" />
  </page>
  <page number="80V" label="f. 80 V" type="folio">
    <image type="TC" jp2Path="Parker/MS_378/JP2_MS_378_TC/378_080_V_TC_46.jp2" width="3590" height="5744" />
    <image type="NC" jp2Path="Parker/MS_378/JP2_MS_378_NC/378_080_V_NC_46.jp2" width="5428" height="7228" />
  </page>
  <page number="81R" label="f. 81 R" type="folio">
    <image type="TC" jp2Path="Parker/MS_378/JP2_MS_378_TC/378_081_R_TC_46.jp2" width="3602" height="5712" />
    <image type="NC" jp2Path="Parker/MS_378/JP2_MS_378_NC/378_081_R_NC_46.jp2" width="5428" height="7228" />
  </page>
  <page number="81V" label="f. 81 V" type="folio">
    <image type="TC" jp2Path="Parker/MS_378/JP2_MS_378_TC/378_081_V_TC_46.jp2" width="3608" height="5721" />
    <image type="NC" jp2Path="Parker/MS_378/JP2_MS_378_NC/378_081_V_NC_46.jp2" width="5428" height="7228" />
  </page>
  <page number="82R" label="f. 82 R" type="folio">
    <image type="TC" jp2Path="Parker/MS_378/JP2_MS_378_TC/378_082_R_TC_46.jp2" width="3614" height="5676" />
    <image type="NC" jp2Path="Parker/MS_378/JP2_MS_378_NC/378_082_R_NC_46.jp2" width="5428" height="7228" />
  </page>
  <page number="82V" label="f. 82 V" type="folio">
    <image type="TC" jp2Path="Parker/MS_378/JP2_MS_378_TC/378_082_V_TC_46.jp2" width="3596" height="5667" />
    <image type="NC" jp2Path="Parker/MS_378/JP2_MS_378_NC/378_082_V_NC_46.jp2" width="5428" height="7228" />
  </page>
  <page number="83R" label="f. 83 R" type="folio">
    <image type="TC" jp2Path="Parker/MS_378/JP2_MS_378_TC/378_083_R_TC_46.jp2" width="3578" height="5676" />
    <image type="NC" jp2Path="Parker/MS_378/JP2_MS_378_NC/378_083_R_NC_46.jp2" width="5428" height="7228" />
  </page>
  <page number="83V" label="f. 83 V" type="folio">
    <image type="TC" jp2Path="Parker/MS_378/JP2_MS_378_TC/378_083_V_TC_46.jp2" width="3578" height="5672" />
    <image type="NC" jp2Path="Parker/MS_378/JP2_MS_378_NC/378_083_V_NC_46.jp2" width="5428" height="7228" />
  </page>
  <page number="84R" label="f. 84 R" type="folio">
    <image type="TC" jp2Path="Parker/MS_378/JP2_MS_378_TC/378_084_R_TC_46.jp2" width="3596" height="5640" />
    <image type="NC" jp2Path="Parker/MS_378/JP2_MS_378_NC/378_084_R_NC_46.jp2" width="5428" height="7228" />
  </page>
  <page number="84V" label="f. 84 V" type="folio">
    <image type="TC" jp2Path="Parker/MS_378/JP2_MS_378_TC/378_084_V_TC_46.jp2" width="3578" height="5624" />
    <image type="NC" jp2Path="Parker/MS_378/JP2_MS_378_NC/378_084_V_NC_46.jp2" width="5428" height="7228" />
  </page>
  <page number="85R" label="f. 85 R" type="folio">
    <image type="TC" jp2Path="Parker/MS_378/JP2_MS_378_TC/378_085_R_TC_46.jp2" width="3572" height="5688" />
    <image type="NC" jp2Path="Parker/MS_378/JP2_MS_378_NC/378_085_R_NC_46.jp2" width="5428" height="7228" />
  </page>
  <page number="85V" label="f. 85 V" type="folio">
    <image type="TC" jp2Path="Parker/MS_378/JP2_MS_378_TC/378_085_V_TC_46.jp2" width="3566" height="5679" />
    <image type="NC" jp2Path="Parker/MS_378/JP2_MS_378_NC/378_085_V_NC_46.jp2" width="5428" height="7228" />
  </page>
  <page number="86R" label="f. 86 R" type="folio">
    <image type="TC" jp2Path="Parker/MS_378/JP2_MS_378_TC/378_086_R_TC_46.jp2" width="3548" height="5689" />
    <image type="NC" jp2Path="Parker/MS_378/JP2_MS_378_NC/378_086_R_NC_46.jp2" width="5428" height="7228" />
  </page>
  <page number="86V" label="f. 86 V" type="folio">
    <image type="TC" jp2Path="Parker/MS_378/JP2_MS_378_TC/378_086_V_TC_46.jp2" width="3553" height="5684" />
    <image type="NC" jp2Path="Parker/MS_378/JP2_MS_378_NC/378_086_V_NC_46.jp2" width="5428" height="7228" />
  </page>
  <page number="87R" label="f. 87 R" type="folio">
    <image type="TC" jp2Path="Parker/MS_378/JP2_MS_378_TC/378_087_R_TC_46.jp2" width="3536" height="5676" />
    <image type="NC" jp2Path="Parker/MS_378/JP2_MS_378_NC/378_087_R_NC_46.jp2" width="5428" height="7228" />
  </page>
  <page number="87V" label="f. 87 V" type="folio">
    <image type="TC" jp2Path="Parker/MS_378/JP2_MS_378_TC/378_087_V_TC_46.jp2" width="3524" height="5678" />
    <image type="NC" jp2Path="Parker/MS_378/JP2_MS_378_NC/378_087_V_NC_46.jp2" width="5428" height="7228" />
  </page>
  <page number="88R" label="f. 88 R" type="folio">
    <image type="TC" jp2Path="Parker/MS_378/JP2_MS_378_TC/378_088_R_TC_46.jp2" width="3554" height="5766" />
    <image type="NC" jp2Path="Parker/MS_378/JP2_MS_378_NC/378_088_R_NC_46.jp2" width="5428" height="7228" />
  </page>
  <page number="88V" label="f. 88 V" type="folio">
    <image type="TC" jp2Path="Parker/MS_378/JP2_MS_378_TC/378_088_V_TC_46.jp2" width="3578" height="5781" />
    <image type="NC" jp2Path="Parker/MS_378/JP2_MS_378_NC/378_088_V_NC_46.jp2" width="5428" height="7228" />
  </page>
  <page number="89R" label="f. 89 R" type="folio">
    <image type="TC" jp2Path="Parker/MS_378/JP2_MS_378_TC/378_089_R_TC_46.jp2" width="3596" height="5760" />
    <image type="NC" jp2Path="Parker/MS_378/JP2_MS_378_NC/378_089_R_NC_46.jp2" width="5428" height="7228" />
  </page>
  <page number="89V" label="f. 89 V" type="folio">
    <image type="TC" jp2Path="Parker/MS_378/JP2_MS_378_TC/378_089_V_TC_46.jp2" width="3613" height="5763" />
    <image type="NC" jp2Path="Parker/MS_378/JP2_MS_378_NC/378_089_V_NC_46.jp2" width="5428" height="7228" />
  </page>
  <page number="90R" label="f. 90 R" type="folio">
    <image type="TC" jp2Path="Parker/MS_378/JP2_MS_378_TC/378_090_R_TC_46.jp2" width="3572" height="5759" />
    <image type="NC" jp2Path="Parker/MS_378/JP2_MS_378_NC/378_090_R_NC_46.jp2" width="5428" height="7228" />
  </page>
  <page number="90V" label="f. 90 V" type="folio">
    <image type="TC" jp2Path="Parker/MS_378/JP2_MS_378_TC/378_090_V_TC_46.jp2" width="3602" height="5751" />
    <image type="NC" jp2Path="Parker/MS_378/JP2_MS_378_NC/378_090_V_NC_46.jp2" width="5428" height="7228" />
  </page>
  <page number="91R" label="f. 91 R" type="folio">
    <image type="TC" jp2Path="Parker/MS_378/JP2_MS_378_TC/378_091_R_TC_46.jp2" width="3620" height="5736" />
    <image type="NC" jp2Path="Parker/MS_378/JP2_MS_378_NC/378_091_R_NC_46.jp2" width="5428" height="7228" />
  </page>
  <page number="91V" label="f. 91 V" type="folio">
    <image type="TC" jp2Path="Parker/MS_378/JP2_MS_378_TC/378_091_V_TC_46.jp2" width="3596" height="5733" />
    <image type="NC" jp2Path="Parker/MS_378/JP2_MS_378_NC/378_091_V_NC_46.jp2" width="5428" height="7228" />
  </page>
  <page number="92R" label="f. 92 R" type="folio">
    <image type="TC" jp2Path="Parker/MS_378/JP2_MS_378_TC/378_092_R_TC_46.jp2" width="3602" height="5736" />
    <image type="NC" jp2Path="Parker/MS_378/JP2_MS_378_NC/378_092_R_NC_46.jp2" width="5428" height="7228" />
  </page>
  <page number="92V" label="f. 92 V" type="folio">
    <image type="TC" jp2Path="Parker/MS_378/JP2_MS_378_TC/378_092_V_TC_46.jp2" width="3608" height="5739" />
    <image type="NC" jp2Path="Parker/MS_378/JP2_MS_378_NC/378_092_V_NC_46.jp2" width="5428" height="7228" />
  </page>
  <page number="93R" label="f. 93 R" type="folio">
    <image type="TC" jp2Path="Parker/MS_378/JP2_MS_378_TC/378_093_R_TC_46.jp2" width="3608" height="5736" />
    <image type="NC" jp2Path="Parker/MS_378/JP2_MS_378_NC/378_093_R_NC_46.jp2" width="5428" height="7228" />
  </page>
  <page number="93V" label="f. 93 V" type="folio">
    <image type="TC" jp2Path="Parker/MS_378/JP2_MS_378_TC/378_093_V_TC_46.jp2" width="3608" height="5733" />
    <image type="NC" jp2Path="Parker/MS_378/JP2_MS_378_NC/378_093_V_NC_46.jp2" width="5428" height="7228" />
  </page>
  <page number="94R" label="f. 94 R" type="folio">
    <image type="TC" jp2Path="Parker/MS_378/JP2_MS_378_TC/378_094_R_TC_46.jp2" width="3560" height="5730" />
    <image type="NC" jp2Path="Parker/MS_378/JP2_MS_378_NC/378_094_R_NC_46.jp2" width="5428" height="7228" />
  </page>
  <page number="94V" label="f. 94 V" type="folio">
    <image type="TC" jp2Path="Parker/MS_378/JP2_MS_378_TC/378_094_V_TC_46.jp2" width="3632" height="5739" />
    <image type="NC" jp2Path="Parker/MS_378/JP2_MS_378_NC/378_094_V_NC_46.jp2" width="5428" height="7228" />
  </page>
  <page number="95R" label="f. 95 R" type="folio">
    <image type="TC" jp2Path="Parker/MS_378/JP2_MS_378_TC/378_095_R_TC_46.jp2" width="3602" height="5694" />
    <image type="NC" jp2Path="Parker/MS_378/JP2_MS_378_NC/378_095_R_NC_46.jp2" width="5428" height="7228" />
  </page>
  <page number="95V" label="f. 95 V" type="folio">
    <image type="TC" jp2Path="Parker/MS_378/JP2_MS_378_TC/378_095_V_TC_46.jp2" width="3602" height="5721" />
    <image type="NC" jp2Path="Parker/MS_378/JP2_MS_378_NC/378_095_V_NC_46.jp2" width="5428" height="7228" />
  </page>
  <page number="96R" label="f. 96 R" type="folio">
    <image type="TC" jp2Path="Parker/MS_378/JP2_MS_378_TC/378_096_R_TC_46.jp2" width="3554" height="5753" />
    <image type="NC" jp2Path="Parker/MS_378/JP2_MS_378_NC/378_096_R_NC_46.jp2" width="5428" height="7228" />
  </page>
  <page number="96V" label="f. 96 V" type="folio">
    <image type="TC" jp2Path="Parker/MS_378/JP2_MS_378_TC/378_096_V_TC_46.jp2" width="3548" height="5757" />
    <image type="NC" jp2Path="Parker/MS_378/JP2_MS_378_NC/378_096_V_NC_46.jp2" width="5428" height="7228" />
  </page>
  <page number="97R" label="f. 97 R" type="folio">
    <image type="TC" jp2Path="Parker/MS_378/JP2_MS_378_TC/378_097_R_TC_46.jp2" width="3626" height="5742" />
    <image type="NC" jp2Path="Parker/MS_378/JP2_MS_378_NC/378_097_R_NC_46.jp2" width="5428" height="7228" />
  </page>
  <page number="97V" label="f. 97 V" type="folio">
    <image type="TC" jp2Path="Parker/MS_378/JP2_MS_378_TC/378_097_V_TC_46.jp2" width="3626" height="5751" />
    <image type="NC" jp2Path="Parker/MS_378/JP2_MS_378_NC/378_097_V_NC_46.jp2" width="5428" height="7228" />
  </page>
  <page number="98R" label="f. 98 R" type="folio">
    <image type="TC" jp2Path="Parker/MS_378/JP2_MS_378_TC/378_098_R_TC_46.jp2" width="3596" height="5700" />
    <image type="NC" jp2Path="Parker/MS_378/JP2_MS_378_NC/378_098_R_NC_46.jp2" width="5428" height="7228" />
  </page>
  <page number="98V" label="f. 98 V" type="folio">
    <image type="TC" jp2Path="Parker/MS_378/JP2_MS_378_TC/378_098_V_TC_46.jp2" width="3638" height="5685" />
    <image type="NC" jp2Path="Parker/MS_378/JP2_MS_378_NC/378_098_V_NC_46.jp2" width="5428" height="7228" />
  </page>
  <page number="99R" label="f. 99 R" type="folio">
    <image type="TC" jp2Path="Parker/MS_378/JP2_MS_378_TC/378_099_R_TC_46.jp2" width="3602" height="5694" />
    <image type="NC" jp2Path="Parker/MS_378/JP2_MS_378_NC/378_099_R_NC_46.jp2" width="5428" height="7228" />
  </page>
  <page number="99V" label="f. 99 V" type="folio">
    <image type="TC" jp2Path="Parker/MS_378/JP2_MS_378_TC/378_099_V_TC_46.jp2" width="3614" height="5691" />
    <image type="NC" jp2Path="Parker/MS_378/JP2_MS_378_NC/378_099_V_NC_46.jp2" width="5428" height="7228" />
  </page>
  <page number="100R" label="f. 100 R" type="folio">
    <image type="TC" jp2Path="Parker/MS_378/JP2_MS_378_TC/378_100_R_TC_46.jp2" width="3578" height="5687" />
    <image type="NC" jp2Path="Parker/MS_378/JP2_MS_378_NC/378_100_R_NC_46.jp2" width="5428" height="7228" />
  </page>
  <page number="100V" label="f. 100 V" type="folio">
    <image type="TC" jp2Path="Parker/MS_378/JP2_MS_378_TC/378_100_V_TC_46.jp2" width="3614" height="5704" />
    <image type="NC" jp2Path="Parker/MS_378/JP2_MS_378_NC/378_100_V_NC_46.jp2" width="5428" height="7228" />
  </page>
  <page number="101R" label="f. 101 R" type="folio">
    <image type="TC" jp2Path="Parker/MS_378/JP2_MS_378_TC/378_101_R_TC_46.jp2" width="3578" height="5688" />
    <image type="NC" jp2Path="Parker/MS_378/JP2_MS_378_NC/378_101_R_NC_46.jp2" width="5428" height="7228" />
  </page>
  <page number="101V" label="f. 101 V" type="folio">
    <image type="TC" jp2Path="Parker/MS_378/JP2_MS_378_TC/378_101_V_TC_46.jp2" width="3608" height="5697" />
    <image type="NC" jp2Path="Parker/MS_378/JP2_MS_378_NC/378_101_V_NC_46.jp2" width="5428" height="7228" />
  </page>
  <page number="102R" label="f. 102 R" type="folio">
    <image type="TC" jp2Path="Parker/MS_378/JP2_MS_378_TC/378_102_R_TC_46.jp2" width="3602" height="5784" />
    <image type="NC" jp2Path="Parker/MS_378/JP2_MS_378_NC/378_102_R_NC_46.jp2" width="5428" height="7228" />
  </page>
  <page number="102V" label="f. 102 V" type="folio">
    <image type="TC" jp2Path="Parker/MS_378/JP2_MS_378_TC/378_102_V_TC_46.jp2" width="3602" height="5763" />
    <image type="NC" jp2Path="Parker/MS_378/JP2_MS_378_NC/378_102_V_NC_46.jp2" width="5428" height="7228" />
  </page>
  <page number="103R" label="f. 103 R" type="folio">
    <image type="TC" jp2Path="Parker/MS_378/JP2_MS_378_TC/378_103_R_TC_46.jp2" width="3585" height="5711" />
    <image type="NC" jp2Path="Parker/MS_378/JP2_MS_378_NC/378_103_R_NC_46.jp2" width="5428" height="7228" />
  </page>
  <page number="103V" label="f. 103 V" type="folio">
    <image type="TC" jp2Path="Parker/MS_378/JP2_MS_378_TC/378_103_V_TC_46.jp2" width="3596" height="5709" />
    <image type="NC" jp2Path="Parker/MS_378/JP2_MS_378_NC/378_103_V_NC_46.jp2" width="5428" height="7228" />
  </page>
  <page number="104R" label="f. 104 R" type="folio">
    <image type="TC" jp2Path="Parker/MS_378/JP2_MS_378_TC/378_104_R_TC_46.jp2" width="3608" height="5677" />
    <image type="NC" jp2Path="Parker/MS_378/JP2_MS_378_NC/378_104_R_NC_46.jp2" width="5428" height="7228" />
  </page>
  <page number="104V" label="f. 104 V" type="folio">
    <image type="TC" jp2Path="Parker/MS_378/JP2_MS_378_TC/378_104_V_TC_46.jp2" width="3590" height="5673" />
    <image type="NC" jp2Path="Parker/MS_378/JP2_MS_378_NC/378_104_V_NC_46.jp2" width="5428" height="7228" />
  </page>
  <page number="105R" label="f. 105 R" type="folio">
    <image type="TC" jp2Path="Parker/MS_378/JP2_MS_378_TC/378_105_R_TC_46.jp2" width="3597" height="5718" />
    <image type="NC" jp2Path="Parker/MS_378/JP2_MS_378_NC/378_105_R_NC_46.jp2" width="5428" height="7228" />
  </page>
  <page number="105V" label="f. 105 V" type="folio">
    <image type="TC" jp2Path="Parker/MS_378/JP2_MS_378_TC/378_105_V_TC_46.jp2" width="3602" height="5727" />
    <image type="NC" jp2Path="Parker/MS_378/JP2_MS_378_NC/378_105_V_NC_46.jp2" width="5428" height="7228" />
  </page>
  <page number="106R" label="f. 106 R" type="folio">
    <image type="TC" jp2Path="Parker/MS_378/JP2_MS_378_TC/378_106_R_TC_46.jp2" width="3680" height="5706" />
    <image type="NC" jp2Path="Parker/MS_378/JP2_MS_378_NC/378_106_R_NC_46.jp2" width="5428" height="7228" />
  </page>
  <page number="106V" label="f. 106 V" type="folio">
    <image type="TC" jp2Path="Parker/MS_378/JP2_MS_378_TC/378_106_V_TC_46.jp2" width="3686" height="5703" />
    <image type="NC" jp2Path="Parker/MS_378/JP2_MS_378_NC/378_106_V_NC_46.jp2" width="5428" height="7228" />
  </page>
  <page number="107R" label="f. 107 R" type="folio">
    <image type="TC" jp2Path="Parker/MS_378/JP2_MS_378_TC/378_107_R_TC_46.jp2" width="3668" height="5658" />
    <image type="NC" jp2Path="Parker/MS_378/JP2_MS_378_NC/378_107_R_NC_46.jp2" width="5428" height="7228" />
  </page>
  <page number="107V" label="f. 107 V" type="folio">
    <image type="TC" jp2Path="Parker/MS_378/JP2_MS_378_TC/378_107_V_TC_46.jp2" width="3680" height="5667" />
    <image type="NC" jp2Path="Parker/MS_378/JP2_MS_378_NC/378_107_V_NC_46.jp2" width="5428" height="7228" />
  </page>
  <page number="108R" label="f. 108 R" type="folio">
    <image type="TC" jp2Path="Parker/MS_378/JP2_MS_378_TC/378_108_R_TC_46.jp2" width="3650" height="5706" />
    <image type="NC" jp2Path="Parker/MS_378/JP2_MS_378_NC/378_108_R_NC_46.jp2" width="5428" height="7228" />
  </page>
  <page number="108V" label="f. 108 V" type="folio">
    <image type="TC" jp2Path="Parker/MS_378/JP2_MS_378_TC/378_108_V_TC_46.jp2" width="3692" height="5709" />
    <image type="NC" jp2Path="Parker/MS_378/JP2_MS_378_NC/378_108_V_NC_46.jp2" width="5428" height="7228" />
  </page>
  <page number="iiiR" label="f. iii R" type="folio">
    <image type="TC" jp2Path="Parker/MS_378/JP2_MS_378_TC/378_iii_R_TC_46.jp2" width="3728" height="5784" />
    <image type="NC" jp2Path="Parker/MS_378/JP2_MS_378_NC/378_iii_R_NC_46.jp2" width="5428" height="7228" />
  </page>
  <page number="iiiV" label="f. iii V" type="folio">
    <image type="TC" jp2Path="Parker/MS_378/JP2_MS_378_TC/378_iii_V_TC_46.jp2" width="3781" height="5787" />
    <image type="NC" jp2Path="Parker/MS_378/JP2_MS_378_NC/378_iii_V_NC_46.jp2" width="5428" height="7228" />
  </page>
  <page number="ivR" label="f. iv R" type="folio">
    <image type="TC" jp2Path="Parker/MS_378/JP2_MS_378_TC/378_iv_R_TC_46.jp2" width="3710" height="5783" />
    <image type="NC" jp2Path="Parker/MS_378/JP2_MS_378_NC/378_iv_R_NC_46.jp2" width="5428" height="7228" />
  </page>
  <page number="ivV" label="f. iv V" type="folio">
    <image type="TC" jp2Path="Parker/MS_378/JP2_MS_378_TC/378_iv_V_TC_46.jp2" width="3817" height="5781" />
    <image type="NC" jp2Path="Parker/MS_378/JP2_MS_378_NC/378_iv_V_NC_46.jp2" width="5428" height="7228" />
  </page>
  <page number="bib" label="Back inside binding" type="folio">
    <image type="TC" jp2Path="Parker/MS_378/JP2_MS_378_TC/378_bib_TC_46.jp2" width="4010" height="5945" />
    <image type="NC" jp2Path="Parker/MS_378/JP2_MS_378_NC/378_bib_NC_46.jp2" width="5428" height="7228" />
  </page>
  <page number="bob" label="Back outside binding" type="folio">
    <image type="TC" jp2Path="Parker/MS_378/JP2_MS_378_TC/378_bob_TC_46.jp2" width="4268" height="5972" />
    <image type="NC" jp2Path="Parker/MS_378/JP2_MS_378_NC/378_bob_NC_46.jp2" width="5428" height="7228" />
  </page>
  <page number="coverblank" label="coverblank" type="blank">
    <image type="TC" jp2Path="" width="0" height="0" />
    <image type="NC" jp2Path="" width="0" height="0" />
  </page>
</collection>